{
"type": "FeatureCollection",
"name": "geo_36_特定施設入居者生活介護（有料老人ホーム）",
"crs": { "type": "name", "properties": { "name": "urn:ogc:def:crs:OGC:1.3:CRS84" } },
"features": [
{ "type": "Feature", "properties": { "内容": "介護付有料老人ホーム　コートダジュール虹の橋【特定施設入居者生活介護（有料老人ホーム）】徳島県徳島市中島田町３丁目６４番地コートダジュール虹の橋", "url": "https://www.kaigokensaku.mhlw.go.jp/36/index.php?action_kouhyou_detail_004_kani=true&JigyosyoCd=3670102221-00&ServiceCd=331&Type=search", "url2": "https://nijinohashikaigo.com/cotodazule/" }, "geometry": { "type": "Point", "coordinates": [ 134.509903200000053, 34.0838423 ] } },
{ "type": "Feature", "properties": { "内容": "介護付き有料老人ホーム　エクセレント徳島【特定施設入居者生活介護（有料老人ホーム）】徳島県徳島市南矢三町1丁目7-51介護付き有料老人ホーム　エクセレント徳島", "url": "https://www.kaigokensaku.mhlw.go.jp/36/index.php?action_kouhyou_detail_004_kani=true&JigyosyoCd=3670102023-00&ServiceCd=331&Type=search", "url2": "http://www.excare.co.jp/" }, "geometry": { "type": "Point", "coordinates": [ 134.532262100000054, 34.0831542 ] } },
{ "type": "Feature", "properties": { "内容": "有料老人ホーム松の実【特定施設入居者生活介護（有料老人ホーム）】徳島県徳島市名東町二丁目479番1有料老人ホーム松の実", "url": "https://www.kaigokensaku.mhlw.go.jp/36/index.php?action_kouhyou_detail_004_kani=true&JigyosyoCd=3670102197-00&ServiceCd=331&Type=search", "url2": "https://kawauchi-clinic.jp/matunomi-home" }, "geometry": { "type": "Point", "coordinates": [ 134.496568499999967, 34.0602447 ] } },
{ "type": "Feature", "properties": { "内容": "メゾン阿波池田【特定施設入居者生活介護（有料老人ホーム）】徳島県三好市池田町シマ717番地1", "url": "https://www.kaigokensaku.mhlw.go.jp/36/index.php?action_kouhyou_detail_004_kani=true&JigyosyoCd=3670600331-00&ServiceCd=331&Type=search", "url2": null }, "geometry": { "type": "Point", "coordinates": [ 133.820111600000018, 34.0275386 ] } },
{ "type": "Feature", "properties": { "内容": "介護付有料老人ホームメゾン阿波池田【特定施設入居者生活介護（有料老人ホーム）】池田町シマ717番地1介護付有料老人ホームメゾン阿波池田", "url": "https://www.kaigokensaku.mhlw.go.jp/36/index.php?action_kouhyou_detail_004_kani=true&JigyosyoCd=3670600422-00&ServiceCd=331&Type=search", "url2": null }, "geometry": { "type": "Point", "coordinates": [ 133.820156, 34.0275405 ] } }
]
}
